LICENSE
MANIFEST.in
README.rst
setup.py
src/django_intellipages.egg-info/PKG-INFO
src/django_intellipages.egg-info/SOURCES.txt
src/django_intellipages.egg-info/dependency_links.txt
src/django_intellipages.egg-info/top_level.txt
src/intellipages/__init__.py
src/intellipages/models.py
src/intellipages/testsettings.py
src/intellipages/templatetags/__init__.py
src/intellipages/templatetags/intellipages.py
src/intellipages/tests/__init__.py