Metadata-Version: 1.0
Name: django-intellipages
Version: 0.1
Summary: This app provides one tiny but useful template filter for page navigation
Home-page: http://github.com/trilan/django-intellipages
Author: Mike Yumatov
Author-email: yumatov@trilan.ru
License: BSD
Platform: UNKNOWN
Classifier: Development Status :: 4 - Beta
Classifier: Framework :: Django
Classifier: Intended Audience :: Developers
Classifier: License :: OSI Approved :: BSD License
Classifier: Operating System :: OS Independent
Classifier: Programming Language :: Python
Classifier: Topic :: Internet :: WWW/HTTP
